{
  "1": [
    2,
    3,
    4,
    5,
    6,
    7,
    8,
    9,
    10,
    11,
    13,
    14,
    17,
    18,
    19,
    20,
    21,
    26,
    30,
    31,
    32,
    33,
    35,
    36,
    37,
    39,
    41,
    45,
    46,
    47,
    48,
    49,
    51,
    52,
    53,
    54,
    56,
    59,
    60,
    62,
    67,
    70,
    73,
    74,
    75,
    77,
    78,
    79,
    80,
    81,
    82,
    83,
    84,
    85,
    86,
    87,
    88,
    89,
    90,
    91,
    92,
    93,
    94,
    95,
    96,
    97,
    98,
    99,
    100,
    101,
    102,
    103,
    104,
    105,
    106,
    107,
    108,
    141,
    142,
    143,
    144,
    147,
    172,
    178,
    179,
    181,
    186,
    187,
    190,
    191,
    192,
    197,
    202,
    206,
    209,
    210,
    211,
    234,
    244,
    255,
    265,
    266,
    269,
    270,
    274,
    275,
    276,
    277,
    280,
    283,
    285,
    287,
    289,
    290,
    291,
    297,
    298,
    299,
    300,
    301,
    302,
    303,
    304,
    306,
    307,
    308,
    309,
    311,
    312,
    313,
    320,
    330,
    336,
    337,
    346,
    351,
    352,
    360,
    366,
    373,
    376,
    377,
    378,
    393,
    394,
    405,
    406,
    407
  ],
  "2": [
    1,
    3,
    5,
    8,
    11,
    14,
    18,
    26,
    30,
    31,
    32,
    33,
    35,
    42,
    80,
    83,
    86,
    91,
    93,
    95,
    98,
    100,
    103,
    146,
    147,
    179,
    187,
    190,
    191,
    192,
    197,
    199,
    202,
    206,
    209,
    210,
    211,
    218,
    255,
    264,
    265,
    269,
    270,
    278,
    284,
    289,
    290,
    291,
    292,
    293,
    294,
    295,
    296,
    303,
    304,
    306,
    307,
    311,
    319,
    337,
    340,
    352,
    353,
    374,
    385,
    388,
    391,
    392,
    393,
    395,
    397,
    403,
    405,
    406,
    407,
    408,
    409
  ],
  "3": [
    1,
    2,
    5,
    7,
    9,
    11,
    21,
    30,
    31,
    80,
    83,
    86,
    91,
    93,
    95,
    98,
    99,
    100,
    141,
    142,
    143,
    144,
    178,
    190,
    218,
    269,
    270,
    273,
    278,
    284,
    309,
    311,
    339,
    349,
    353,
    357,
    359,
    386,
    395,
    401
  ],
  "4": [
    1,
    8,
    14,
    21,
    30,
    86,
    98,
    100,
    104,
    190,
    196,
    296
  ],
  "5": [
    1,
    2,
    14,
    30,
    95,
    104,
    120,
    202,
    234,
    280,
    289
  ],
  "6": [
    1,
    30,
    108,
    155
  ],
  "7": [
    1,
    2,
    3,
    4,
    9,
    10,
    11,
    12,
    26,
    30,
    32,
    90,
    95,
    99,
    108,
    109,
    145,
    165,
    178,
    179,
    205,
    213,
    218,
    225,
    241,
    255,
    265,
    309,
    311,
    312,
    313,
    339,
    346,
    349,
    353,
    357,
    359,
    360,
    366,
    372,
    373,
    374,
    376,
    377,
    386,
    401,
    407,
    410
  ],
  "8": [
    1,
    2,
    3,
    4,
    5,
    9,
    14,
    18,
    19,
    21,
    22,
    23,
    26,
    27,
    29,
    30,
    31,
    32,
    33,
    42,
    43,
    45,
    46,
    51,
    55,
    62,
    63,
    67,
    69,
    70,
    73,
    77,
    80,
    82,
    83,
    86,
    91,
    93,
    95,
    96,
    98,
    100,
    106,
    107,
    108,
    118,
    119,
    124,
    125,
    172,
    178,
    180,
    196,
    209,
    218,
    225,
    232,
    255,
    270,
    290,
    306,
    307,
    308,
    311,
    312,
    313,
    316,
    319,
    320,
    323,
    330,
    337,
    352,
    373,
    374,
    385,
    394,
    405,
    406,
    407,
    408,
    409
  ],
  "9": [
    1,
    2,
    3,
    5,
    7,
    8,
    10,
    11,
    12,
    13,
    14,
    15,
    16,
    17,
    18,
    19,
    20,
    21,
    27,
    30,
    31,
    33,
    35,
    36,
    37,
    39,
    41,
    45,
    46,
    47,
    51,
    54,
    56,
    58,
    59,
    61,
    62,
    67,
    70,
    71,
    73,
    75,
    77,
    78,
    79,
    80,
    81,
    84,
    90,
    91,
    93,
    95,
    96,
    98,
    99,
    100,
    104,
    107,
    108,
    135,
    172,
    190,
    269,
    270,
    272,
    297,
    298,
    299,
    300,
    302,
    304,
    306,
    309,
    311,
    312,
    313,
    316,
    319,
    342,
    343,
    346,
    347,
    348,
    349,
    351,
    354,
    355,
    356,
    380,
    411
  ],
  "10": [
    1,
    2,
    8,
    9,
    13,
    33,
    79,
    98,
    108,
    111,
    159,
    172,
    178,
    244,
    246,
    254,
    255,
    256,
    261,
    262,
    263,
    265,
    267,
    298,
    377,
    410,
    411
  ],
  "11": [
    1,
    7,
    8,
    14,
    18,
    20,
    26,
    30,
    40,
    51,
    52,
    59,
    72,
    78,
    79,
    83,
    144,
    146,
    147,
    148,
    157,
    158,
    162,
    163,
    166,
    170,
    171,
    172,
    174,
    175,
    178,
    182,
    188,
    193,
    194,
    195,
    198,
    202,
    206,
    208,
    209,
    210,
    211,
    214,
    220,
    227,
    238,
    240,
    241,
    242,
    257,
    259,
    260,
    266,
    269,
    270,
    272,
    274,
    275,
    277,
    278,
    280,
    281,
    282,
    284,
    286,
    289,
    290,
    291,
    292,
    293,
    294,
    295,
    296,
    298,
    299,
    300,
    302,
    304,
    309,
    316,
    317,
    321,
    335,
    339,
    343,
    345,
    351,
    352,
    359,
    374,
    378,
    391,
    403,
    411
  ],
  "12": [
    1,
    2,
    7,
    9,
    11,
    145,
    165,
    179,
    205,
    213,
    218,
    225,
    229,
    272
  ],
  "13": [
    17,
    18,
    19,
    20,
    21,
    22,
    25,
    26,
    30,
    36,
    42,
    45,
    48,
    51,
    72,
    74,
    78,
    85,
    90,
    91,
    93,
    95,
    105,
    106,
    109,
    115,
    119,
    125,
    128,
    130,
    132,
    134,
    135,
    137,
    138,
    139,
    196,
    203,
    222,
    244,
    256,
    307,
    311,
    349,
    410
  ],
  "14": [
    8,
    9,
    10,
    13,
    15,
    26,
    27,
    29,
    30,
    50,
    51,
    52,
    108,
    109,
    118,
    123,
    141,
    142,
    145,
    203,
    247,
    249,
    256,
    262,
    298,
    300,
    306,
    312,
    313,
    316,
    327,
    373,
    396,
    410
  ],
  "15": [
    3,
    8,
    10,
    13,
    14,
    18,
    19,
    21,
    22,
    23,
    30,
    33,
    35,
    37,
    46,
    61,
    62,
    66,
    68,
    71,
    73,
    77,
    79,
    108,
    114,
    118,
    125,
    190,
    306,
    321,
    373,
    374,
    398
  ],
  "16": [
    8,
    15,
    17,
    18,
    19,
    20,
    22,
    60,
    67,
    73,
    75,
    82,
    108,
    255,
    262,
    298,
    299,
    302,
    304,
    306,
    309,
    312,
    316,
    321,
    348,
    373,
    374,
    377,
    379,
    401,
    405,
    406,
    407,
    409
  ],
  "17": [
    1,
    9,
    13,
    14,
    30,
    64,
    70,
    74,
    77,
    78,
    79,
    80,
    81,
    82,
    84,
    85,
    86,
    88,
    94,
    108,
    298,
    299,
    304
  ],
  "18": [
    8,
    9,
    13,
    14,
    15,
    30,
    35,
    36,
    37,
    39,
    40,
    42,
    45,
    60,
    241,
    298,
    299,
    304,
    306,
    321
  ],
  "19": [
    8,
    10,
    13,
    15,
    18,
    20,
    33,
    56,
    298,
    299,
    304,
    321,
    394
  ],
  "20": [
    8,
    13,
    14,
    15,
    17,
    18,
    36,
    38,
    45,
    46,
    60,
    75,
    262,
    297,
    298,
    299,
    300,
    302,
    303,
    304,
    309,
    310,
    335,
    348,
    349,
    373,
    374,
    375,
    377,
    378,
    379
  ],
  "21": [
    1,
    3,
    4,
    8,
    9,
    14,
    17,
    22,
    23,
    24,
    25,
    29,
    30,
    38,
    46,
    49,
    50,
    51,
    53,
    54,
    67,
    70,
    73,
    75,
    78,
    86,
    96,
    106,
    107,
    130,
    142,
    232,
    237,
    312
  ],
  "22": [
    4,
    8,
    9,
    13,
    14,
    21,
    23,
    30,
    46,
    54,
    67,
    70,
    73,
    96,
    312
  ],
  "23": [
    8,
    13,
    14,
    15,
    21,
    22,
    58,
    60,
    67,
    73,
    74,
    109,
    115,
    116,
    117,
    118,
    125,
    152,
    256,
    410
  ],
  "24": [
    5,
    11,
    231,
    234,
    237,
    241,
    242
  ],
  "25": [
    19,
    21,
    106,
    130,
    131,
    151,
    222,
    231
  ],
  "26": [
    11,
    27,
    28,
    30,
    144,
    145,
    158,
    165,
    179,
    182,
    188,
    193,
    194,
    198,
    199,
    205,
    208,
    209,
    210,
    211,
    213,
    218,
    229,
    231,
    232,
    233,
    234,
    241,
    242,
    277,
    281,
    283
  ],
  "27": [
    11,
    26,
    142,
    144,
    146,
    148,
    182,
    194,
    198,
    206,
    213,
    220,
    230,
    234,
    278,
    279,
    283,
    284,
    285,
    288
  ],
  "28": [
    9,
    26,
    108,
    111,
    116,
    117,
    119,
    124,
    172,
    189,
    302,
    325,
    339,
    345,
    349,
    351,
    352,
    357
  ],
  "29": [
    8,
    9,
    10,
    14,
    15,
    21,
    22,
    23,
    26,
    59,
    60
  ],
  "30": [
    1,
    2,
    3,
    5,
    8,
    9,
    11,
    26,
    31,
    32,
    33,
    35,
    42,
    80,
    83,
    86,
    91,
    93,
    95,
    98,
    100,
    103,
    109,
    110,
    113,
    115,
    128,
    132,
    146,
    147,
    179,
    187,
    190,
    191,
    192,
    197,
    199,
    202,
    206,
    209,
    210,
    211,
    218,
    255,
    264,
    265,
    269,
    270,
    278,
    284,
    289,
    290,
    291,
    292,
    293,
    294,
    295,
    296,
    303,
    304,
    306,
    307,
    311,
    319,
    337,
    340,
    352,
    353,
    374,
    385,
    388,
    391,
    392,
    393,
    395,
    397,
    403,
    405,
    406,
    407,
    408,
    409
  ],
  "31": [
    1,
    2,
    3,
    5,
    8,
    30,
    33,
    98,
    391
  ],
  "32": [
    1,
    2,
    3,
    5,
    14,
    18,
    26,
    30,
    33,
    35,
    42,
    80,
    86,
    91,
    93,
    98,
    100,
    146,
    147,
    187,
    255,
    265,
    352,
    395
  ],
  "33": [
    1,
    8,
    9,
    34,
    124,
    135,
    189,
    299,
    302,
    342,
    343,
    347,
    410
  ],
  "34": [
    33,
    135,
    136,
    179,
    189,
    218,
    222,
    225,
    229,
    231,
    256,
    299,
    347,
    410
  ],
  "35": [
    8,
    9,
    13,
    15,
    18,
    30,
    36,
    37,
    38,
    39,
    40,
    41,
    42,
    43,
    44,
    45,
    297,
    299,
    306,
    321
  ],
  "36": [
    9,
    14,
    18,
    30,
    35,
    37,
    39,
    41,
    60,
    75,
    217,
    218,
    241,
    304
  ],
  "37": [
    8,
    9,
    13,
    15,
    18,
    38,
    321
  ],
  "38": [
    8,
    9,
    15,
    18,
    35,
    36,
    37,
    39,
    41,
    60,
    75,
    217,
    218,
    241,
    298,
    299,
    302,
    304,
    316,
    318,
    339
  ],
  "39": [
    8,
    9,
    15,
    18,
    20,
    30,
    35,
    36,
    37,
    38,
    41,
    42,
    44,
    60,
    100,
    298,
    302,
    306
  ],
  "40": [
    9,
    14,
    18,
    30,
    36,
    39,
    42,
    60,
    241,
    306
  ],
  "41": [
    18,
    35,
    36,
    75,
    102,
    255,
    306
  ],
  "42": [
    18,
    30,
    35,
    36,
    39,
    40,
    60,
    99,
    100,
    304
  ],
  "43": [
    4,
    14,
    15,
    44,
    145
  ],
  "44": [
    4,
    15,
    21,
    22,
    39
  ],
  "45": [
    8,
    13,
    18,
    35,
    37,
    38,
    39,
    42,
    46,
    48,
    49,
    50,
    54,
    56,
    67,
    70,
    72,
    141,
    241,
    298,
    299,
    300,
    302,
    304,
    306,
    321,
    394
  ],
  "46": [
    14,
    15,
    18,
    22,
    26,
    48,
    49,
    50,
    51,
    59,
    61,
    70,
    74,
    114,
    132
  ],
  "47": [
    8,
    9,
    45,
    46,
    52,
    54,
    56,
    61,
    94,
    101,
    103,
    108,
    255,
    298,
    300,
    302,
    304,
    306,
    308,
    311,
    312,
    313,
    314,
    315,
    316,
    318,
    320,
    321,
    325,
    330,
    334,
    336,
    349,
    369,
    392,
    393,
    397,
    405,
    406,
    407,
    408
  ],
  "48": [
    13,
    14,
    45,
    46,
    49,
    59,
    61,
    115
  ],
  "49": [
    15,
    22,
    45,
    46,
    48,
    50,
    53
  ],
  "50": [
    45,
    46,
    48
  ],
  "51": [
    1,
    11,
    14,
    21,
    46,
    49,
    180
  ],
  "52": [
    14,
    46,
    47,
    51,
    56,
    306,
    308,
    311,
    314
  ],
  "53": [
    38,
    49,
    50
  ],
  "54": [
    20,
    38,
    45,
    47,
    48,
    300,
    309,
    311,
    315,
    316,
    318,
    319,
    355,
    356,
    363,
    370,
    391
  ],
  "55": [
    8,
    18,
    19,
    45,
    51,
    255,
    270,
    306,
    310,
    316,
    330,
    335,
    370
  ],
  "56": [
    1,
    2,
    3,
    13,
    14,
    30,
    57,
    128,
    129,
    262,
    311,
    315,
    393,
    397
  ],
  "57": [
    56,
    262,
    298,
    300,
    302,
    401
  ],
  "58": [
    1,
    10,
    13,
    17,
    21,
    26,
    30,
    59,
    60,
    61,
    65,
    82,
    85,
    108,
    109,
    196,
    203,
    300,
    302,
    373,
    410
  ],
  "59": [
    4,
    5,
    8,
    14,
    15,
    16,
    17,
    18,
    19,
    20,
    21,
    26,
    30,
    33,
    58,
    60,
    61,
    62,
    64,
    65,
    83,
    108,
    209
  ],
  "60": [
    14,
    15,
    16,
    17,
    18,
    19,
    20,
    23,
    59,
    74,
    108,
    115
  ],
  "61": [
    14,
    15,
    17,
    29,
    46,
    48,
    58,
    59,
    60,
    79,
    108,
    114
  ],
  "62": [
    14,
    15,
    16,
    18,
    20,
    45,
    59,
    60,
    63,
    64,
    108,
    394
  ],
  "63": [
    8,
    14,
    59,
    60,
    64,
    65,
    108,
    196,
    338,
    394
  ],
  "64": [
    14,
    19,
    46,
    48,
    59,
    60,
    61,
    63,
    70,
    83,
    108,
    338,
    394
  ],
  "65": [
    58,
    59,
    60,
    62,
    108
  ],
  "66": [
    9,
    13,
    14,
    15,
    18,
    35,
    36,
    37,
    41,
    45,
    63
  ],
  "67": [
    14,
    26,
    45,
    68,
    144,
    410
  ],
  "68": [
    14,
    15,
    67
  ],
  "69": [
    67,
    68,
    108
  ],
  "70": [
    9,
    14,
    15,
    17,
    26,
    35,
    37,
    46,
    62,
    71,
    77,
    80,
    82,
    85,
    144,
    234,
    247
  ],
  "71": [
    9,
    14,
    15,
    26,
    46,
    70,
    80,
    233
  ],
  "72": [
    9,
    18,
    35,
    45,
    70,
    71,
    105,
    300,
    302
  ],
  "73": [
    8,
    9,
    13,
    14,
    15,
    21,
    22,
    23,
    67,
    74,
    106,
    115,
    116,
    117,
    118,
    119,
    120,
    125,
    256,
    410
  ],
  "74": [
    4,
    13,
    14,
    15,
    16,
    17,
    18,
    19,
    20,
    21,
    22,
    23,
    37,
    66,
    73,
    77,
    373,
    374
  ],
  "75": [
    8,
    16,
    17,
    18,
    20,
    21,
    76,
    106,
    302
  ],
  "76": [
    75,
    298,
    300,
    302
  ],
  "77": [
    9,
    13,
    17,
    37,
    78,
    79,
    80,
    81,
    82,
    83,
    84,
    85,
    86,
    87,
    88,
    89,
    90,
    91,
    92,
    93,
    94,
    95,
    96,
    97,
    108,
    241,
    242
  ],
  "78": [
    1,
    5,
    9,
    11,
    17,
    18,
    77,
    79,
    80,
    81,
    82,
    83,
    84,
    85,
    86,
    87,
    88,
    89,
    90,
    91,
    92,
    93,
    94,
    95,
    96,
    97,
    98,
    108,
    241
  ],
  "79": [
    1,
    3,
    8,
    9,
    10,
    14,
    15,
    17,
    20,
    22,
    46,
    48,
    61,
    77,
    78,
    80,
    81,
    82,
    83,
    84,
    85,
    86,
    87,
    88,
    89,
    90,
    91
  ],
  "80": [
    1,
    3,
    8,
    9,
    11,
    15,
    17,
    21,
    30,
    33,
    34,
    77,
    78,
    79,
    81,
    82,
    83,
    84,
    85,
    86,
    87,
    88,
    89,
    90,
    91,
    92,
    93,
    94,
    95,
    96,
    97,
    98,
    99,
    100,
    380,
    381,
    382,
    383
  ],
  "81": [
    1,
    3,
    8,
    9,
    17,
    77,
    78,
    79,
    80,
    82,
    83,
    84,
    85,
    86,
    87,
    88,
    89,
    90,
    108
  ],
  "82": [
    9,
    14,
    17,
    20,
    26,
    77,
    78,
    79,
    80,
    81,
    83,
    84,
    85,
    87,
    88,
    90,
    91
  ],
  "83": [
    1,
    2,
    9,
    11,
    17,
    26,
    30,
    77,
    78,
    79,
    80,
    81,
    82,
    241,
    242,
    297,
    298,
    299,
    304
  ],
  "84": [
    1,
    5,
    9,
    17,
    26,
    77,
    78,
    79,
    80,
    81,
    82,
    83,
    108
  ],
  "85": [
    9,
    14,
    17,
    77,
    78,
    79,
    80,
    81,
    82,
    83,
    84,
    86,
    87,
    88,
    89
  ],
  "86": [
    1,
    2,
    3,
    4,
    9,
    14,
    17,
    21,
    30,
    77,
    78,
    79,
    80,
    81,
    82,
    83,
    84,
    85,
    87,
    88,
    89,
    90,
    91,
    98,
    108,
    178
  ],
  "87": [
    17,
    77,
    78,
    79,
    80,
    81,
    82,
    83,
    84,
    85,
    86,
    88,
    89,
    90,
    108,
    175,
    297,
    298
  ],
  "88": [
    17,
    47,
    59,
    64,
    77,
    78,
    79,
    80,
    81,
    82,
    83,
    84,
    85,
    86,
    87,
    89,
    90,
    91,
    92,
    93,
    94,
    95,
    96,
    97,
    108,
    175,
    297,
    298
  ],
  "89": [
    17,
    77,
    78,
    79,
    80,
    81,
    82,
    83,
    108,
    175
  ],
  "90": [
    1,
    5,
    9,
    17,
    30,
    77,
    78,
    79,
    80,
    91,
    92,
    93,
    94,
    95,
    96,
    97,
    98,
    103,
    107,
    108
  ],
  "91": [
    1,
    2,
    5,
    9,
    18,
    30,
    77,
    78,
    79,
    80,
    81,
    82,
    92,
    93,
    94,
    95,
    96,
    97,
    98,
    99,
    100
  ],
  "92": [
    77,
    78,
    79,
    80,
    81,
    82,
    83,
    84,
    85,
    86,
    87,
    88,
    89,
    90,
    91,
    93,
    94,
    95,
    96,
    97,
    158,
    213,
    233
  ],
  "93": [
    77,
    78,
    80,
    91,
    92,
    94,
    95,
    96,
    97,
    98,
    99,
    100,
    158,
    172,
    213,
    241,
    299
  ],
  "94": [
    77,
    78,
    79,
    80,
    81,
    82,
    83,
    84,
    85,
    86,
    87,
    88,
    89,
    90,
    91,
    92,
    93,
    95,
    96,
    97,
    172,
    308
  ],
  "95": [
    1,
    5,
    14,
    77,
    78,
    79,
    80,
    91,
    92,
    93,
    94,
    96,
    97,
    98,
    306,
    310,
    312
  ],
  "96": [
    1,
    5,
    8,
    9,
    17,
    46,
    77,
    78,
    79,
    80,
    81,
    91,
    92,
    93,
    94,
    95,
    97,
    98,
    99,
    233,
    297,
    299
  ],
  "97": [
    8,
    9,
    77,
    81,
    91,
    92,
    93,
    94,
    95,
    96
  ],
  "98": [
    1,
    2,
    3,
    4,
    5,
    8,
    9,
    10,
    17,
    18,
    21,
    30,
    32,
    45,
    99,
    100,
    101,
    102,
    178,
    186,
    289,
    298,
    300,
    302
  ],
  "99": [
    1,
    3,
    7,
    9,
    21,
    98,
    100,
    101,
    102,
    108,
    298,
    300,
    302,
    304,
    339,
    346,
    349,
    381
  ],
  "100": [
    1,
    2,
    3,
    5,
    8,
    9,
    21,
    30,
    31,
    98,
    99,
    101,
    102,
    303,
    304
  ],
  "101": [
    1,
    2,
    3,
    4,
    9,
    45,
    47,
    98,
    99,
    100,
    102,
    298,
    300,
    302,
    304,
    339,
    392
  ],
  "102": [
    9,
    30,
    56,
    98,
    99,
    100,
    101,
    289,
    299
  ],
  "103": [
    30,
    42,
    78,
    90,
    91,
    95,
    97,
    98,
    100,
    299,
    304,
    316,
    334,
    344,
    354,
    379,
    381,
    382,
    407
  ],
  "104": [
    14,
    17,
    18,
    80,
    105,
    300,
    302,
    304
  ],
  "105": [
    14,
    17,
    18,
    37,
    71,
    72,
    77,
    80,
    104,
    109,
    300,
    302,
    304,
    306,
    316
  ],
  "106": [
    4,
    17,
    21,
    22,
    24,
    30,
    75,
    86,
    103,
    107,
    130,
    204,
    232,
    237,
    242,
    298
  ],
  "107": [
    1,
    5,
    8,
    9,
    30,
    70,
    71,
    78,
    79,
    85,
    90,
    98,
    103,
    106
  ],
  "108": [
    1,
    3,
    8,
    9,
    10,
    12,
    13,
    14,
    17,
    33,
    34,
    42,
    51,
    59,
    60,
    63,
    64,
    70,
    71,
    72,
    77,
    99,
    100,
    112,
    123,
    244,
    249,
    256,
    323,
    339,
    342,
    346,
    372,
    381,
    384,
    385,
    410
  ],
  "109": [
    8,
    9,
    10,
    13,
    14,
    15,
    16,
    17,
    18,
    19,
    20,
    21,
    26,
    30,
    53,
    107,
    110,
    111,
    112,
    113,
    114,
    115,
    116,
    117,
    118,
    119,
    120,
    121,
    122,
    123,
    124,
    125,
    126,
    127,
    128,
    129,
    130,
    131,
    132,
    133,
    134,
    135,
    136,
    137,
    145,
    190,
    204,
    241,
    242,
    256,
    272,
    373,
    410
  ],
  "110": [
    1,
    7,
    12,
    13,
    14,
    23,
    107,
    109,
    113,
    114,
    115,
    116,
    117,
    118,
    121,
    178,
    196,
    256,
    410
  ],
  "111": [
    7,
    15,
    23,
    48,
    99,
    112,
    124,
    267,
    339,
    347,
    349,
    359,
    374,
    394
  ],
  "112": [
    3,
    7,
    48,
    99,
    111,
    115,
    116,
    152,
    196,
    231,
    233,
    256,
    267,
    298,
    324,
    339,
    347,
    349,
    359,
    374,
    394,
    410
  ],
  "113": [
    115,
    121,
    233,
    235,
    237
  ],
  "114": [
    14,
    15,
    16,
    17,
    18,
    19,
    20,
    21,
    22,
    23,
    61,
    62,
    68,
    71,
    110,
    113,
    118,
    125,
    233,
    234
  ],
  "115": [
    1,
    8,
    10,
    109,
    114,
    116,
    117,
    118,
    119,
    120,
    121,
    122,
    123,
    124,
    178,
    179,
    190,
    191,
    192,
    410
  ],
  "116": [
    1,
    8,
    13,
    14,
    15,
    73,
    114,
    115,
    117,
    118,
    119,
    120,
    121,
    123,
    178,
    190,
    256,
    410
  ],
  "117": [
    114,
    115,
    116,
    120,
    121
  ],
  "118": [
    1,
    74,
    109,
    114,
    115,
    116,
    117,
    119,
    124
  ],
  "119": [
    8,
    14,
    25,
    113,
    114,
    115,
    116,
    117,
    120,
    121,
    179,
    180,
    181,
    190,
    191
  ],
  "120": [
    1,
    5,
    23,
    115,
    117,
    119,
    121,
    122,
    178
  ],
  "121": [
    113,
    115,
    116
  ],
  "122": [
    1,
    162,
    163,
    164,
    178,
    179,
    190,
    202,
    222,
    233,
    272
  ],
  "123": [
    13,
    14,
    48,
    73,
    74,
    108,
    109,
    112,
    116,
    164,
    203,
    256,
    410,
    411
  ],
  "124": [
    9,
    108,
    111,
    116,
    117,
    118,
    172,
    189,
    244,
    345,
    349,
    351,
    357
  ],
  "125": [
    13,
    15,
    21,
    22,
    23,
    24,
    73,
    74,
    109,
    110,
    113,
    114,
    115,
    116,
    117,
    118,
    119,
    120,
    121,
    122,
    123,
    126,
    127,
    128,
    129,
    130,
    131,
    132,
    133,
    134,
    135,
    136,
    137,
    179,
    196,
    204,
    222
  ],
  "126": [
    3,
    15,
    21,
    23,
    73,
    109,
    110,
    113,
    125,
    127,
    178,
    179,
    196,
    202,
    298,
    410
  ],
  "127": [
    14,
    108,
    110,
    126,
    193,
    195,
    225,
    233,
    410
  ],
  "128": [
    13,
    109,
    110,
    125,
    129,
    130,
    135,
    233,
    256,
    410
  ],
  "129": [
    14,
    110,
    115,
    125,
    126,
    127,
    128,
    134,
    178,
    193,
    195,
    196,
    202,
    203,
    204,
    222,
    225,
    231,
    233,
    411
  ],
  "130": [
    21,
    106,
    131,
    204
  ],
  "131": [
    21,
    109,
    110,
    115,
    125,
    126,
    127,
    128,
    129,
    130,
    193,
    195,
    196,
    202,
    204,
    222,
    225,
    231
  ],
  "132": [
    128,
    133,
    179,
    196,
    202,
    204,
    222,
    275,
    292,
    296,
    410
  ],
  "133": [
    123,
    128,
    132,
    158,
    164,
    196,
    202,
    203
  ],
  "134": [
    13,
    14,
    109,
    110,
    115,
    127,
    128,
    129,
    193,
    195,
    202,
    204,
    222,
    225,
    231,
    233
  ],
  "135": [
    2,
    8,
    9,
    10,
    14,
    15,
    16,
    18,
    19,
    20,
    30,
    33,
    34,
    46,
    58,
    59,
    60,
    61,
    67,
    68,
    69,
    70,
    71,
    72,
    73,
    74,
    75,
    76,
    86,
    99,
    100,
    105,
    136,
    196,
    222,
    225,
    231,
    233,
    251,
    256,
    339,
    342,
    343,
    346,
    347,
    349,
    410
  ],
  "136": [
    33,
    34,
    115,
    126,
    128,
    129,
    135,
    222,
    225,
    231
  ],
  "137": [
    9,
    10,
    13,
    23,
    110,
    138,
    139,
    140,
    161,
    172,
    244,
    298,
    339,
    407,
    410
  ],
  "138": [
    1,
    12,
    13,
    109,
    110,
    115,
    137,
    139,
    140,
    161,
    196,
    256,
    298,
    410
  ],
  "139": [
    10,
    13,
    109,
    110,
    115,
    137,
    138,
    161,
    165,
    172,
    256,
    410
  ],
  "140": [
    12,
    13,
    26,
    109,
    115,
    122,
    137,
    256,
    410,
    411
  ],
  "141": [
    3,
    14,
    21,
    26,
    27,
    30,
    45,
    82,
    142,
    143,
    144,
    172,
    234,
    247,
    253,
    298
  ],
  "142": [
    14,
    21,
    26,
    27,
    30,
    45,
    59,
    63,
    82,
    108,
    141,
    143,
    144,
    172,
    234,
    247,
    249,
    253,
    265,
    298
  ],
  "143": [
    63,
    141,
    142,
    298
  ],
  "144": [
    2,
    3,
    7,
    11,
    12,
    21,
    26,
    28,
    30,
    35,
    45,
    51,
    77,
    108,
    137,
    140,
    141,
    142,
    143,
    162,
    209,
    234,
    259,
    272
  ],
  "145": [
    1,
    7,
    11,
    12,
    146,
    147,
    148,
    149,
    150,
    151,
    152,
    153,
    154,
    155,
    156,
    157,
    158,
    159,
    160,
    161,
    162,
    163,
    164,
    174,
    182,
    194,
    206,
    214,
    220,
    227,
    230,
    242,
    243,
    259,
    260,
    271,
    322,
    323,
    329,
    362
  ],
  "146": [
    11,
    145,
    147,
    148,
    159,
    208,
    298
  ],
  "147": [
    8,
    11,
    14,
    26,
    145,
    146,
    209,
    210
  ],
  "148": [
    144,
    145,
    149,
    156,
    160,
    163,
    209,
    234,
    269
  ],
  "149": [
    5,
    11,
    26,
    144,
    145,
    146,
    148,
    209,
    234,
    238
  ],
  "150": [
    28,
    114,
    153,
    157,
    158,
    240
  ],
  "151": [
    21,
    25,
    106,
    108,
    152,
    158,
    202,
    236,
    237
  ],
  "152": [
    23,
    116,
    145,
    151,
    157,
    158
  ],
  "153": [
    12,
    150,
    154,
    155,
    158,
    161,
    162,
    165,
    166,
    167,
    168,
    171,
    172,
    174,
    202
  ],
  "154": [
    153,
    158,
    163,
    172
  ],
  "155": [
    6,
    153,
    154,
    161,
    172,
    174
  ],
  "156": [
    7,
    11,
    26,
    28,
    145,
    149,
    150,
    151,
    157,
    168,
    169,
    170,
    183,
    188,
    194,
    195,
    196,
    200,
    233,
    234,
    238,
    240,
    285,
    288
  ],
  "157": [
    11,
    26,
    28,
    114,
    150,
    152,
    156,
    158,
    170,
    183,
    233,
    234,
    239,
    240,
    259
  ],
  "158": [
    10,
    14,
    26,
    93,
    142,
    145,
    150,
    154,
    157,
    159,
    160,
    163,
    164,
    172,
    173,
    175,
    182,
    184,
    187,
    188,
    193,
    194,
    198,
    199,
    202,
    206,
    207,
    213,
    224,
    230,
    234,
    245,
    246,
    255,
    257,
    259,
    260,
    262,
    269,
    271,
    293,
    295,
    306,
    316,
    321,
    322,
    323,
    329,
    339,
    362
  ],
  "159": [
    93,
    114,
    151,
    158,
    160,
    162,
    172,
    181,
    182,
    193,
    194,
    196,
    198,
    231,
    236,
    237,
    242,
    243,
    300,
    302,
    304,
    316,
    321,
    322,
    323,
    339
  ],
  "160": [
    114,
    158,
    159,
    162,
    163,
    172,
    195,
    231,
    236,
    237,
    242,
    243,
    256,
    266,
    321
  ],
  "161": [
    6,
    13,
    15,
    111,
    114,
    115,
    116,
    117,
    124,
    137,
    138,
    139,
    150,
    153,
    154,
    155,
    158,
    163,
    165,
    166,
    170,
    171,
    172,
    182,
    184,
    219,
    220,
    221,
    225,
    226,
    227,
    228,
    234,
    236,
    239,
    256,
    262,
    325
  ],
  "162": [
    3,
    7,
    11,
    26,
    144,
    145,
    158,
    159,
    160,
    163,
    165,
    172,
    184,
    222,
    231,
    277,
    281,
    283,
    296
  ],
  "163": [
    1,
    3,
    5,
    7,
    11,
    12,
    21,
    26,
    144,
    145,
    148,
    151,
    153,
    158,
    161,
    162,
    164,
    172,
    202,
    222,
    231,
    242,
    262,
    271,
    321,
    368,
    390,
    410,
    411
  ],
  "164": [
    14,
    116,
    123,
    133,
    145,
    162,
    163,
    203,
    410
  ],
  "165": [
    12,
    158,
    159,
    160,
    161,
    162,
    166,
    167,
    168,
    169,
    170,
    171,
    172,
    173,
    174,
    175,
    176,
    177,
    206,
    230,
    234,
    235,
    236,
    237,
    238,
    239,
    240,
    243,
    246,
    252,
    260,
    269,
    272,
    277,
    279,
    281,
    283,
    285,
    286,
    297,
    298,
    299,
    300,
    302,
    304,
    321,
    326,
    328,
    329,
    332,
    340,
    411
  ],
  "166": [
    11,
    165,
    209,
    287
  ],
  "167": [
    5,
    26,
    141,
    142,
    144,
    165,
    166,
    168,
    169,
    199,
    234,
    238
  ],
  "168": [
    165,
    166,
    240
  ],
  "169": [
    165,
    168,
    170,
    173,
    240
  ],
  "170": [
    26,
    28,
    157,
    169,
    183,
    195,
    240
  ],
  "171": [
    7,
    11,
    26,
    144,
    165,
    166,
    168,
    170,
    195,
    205,
    209,
    233,
    240,
    241,
    242
  ],
  "172": [
    1,
    7,
    9,
    10,
    12,
    26,
    27,
    89,
    108,
    118,
    122,
    134,
    137,
    139,
    153,
    154,
    155,
    158,
    160,
    162,
    163,
    164,
    165,
    168,
    174,
    175,
    176,
    178,
    179,
    182,
    202,
    205,
    206,
    213,
    214,
    215,
    225,
    229,
    230,
    231,
    234,
    235,
    236,
    237,
    238,
    239,
    240,
    242,
    243,
    244,
    245,
    246,
    247,
    248,
    250,
    252,
    253,
    255,
    299,
    317,
    321,
    326,
    327,
    329,
    331,
    332,
    339,
    404,
    410,
    411
  ],
  "173": [
    12,
    21,
    158,
    165,
    169,
    172,
    174
  ],
  "174": [
    1,
    153,
    165,
    166,
    167,
    168,
    169,
    170,
    172,
    255,
    277,
    279,
    281,
    283,
    296,
    297,
    299
  ],
  "175": [
    12,
    112,
    158,
    172,
    232,
    233,
    234
  ],
  "176": [
    11,
    12,
    26,
    141,
    142,
    144,
    158,
    165,
    172,
    175,
    177,
    233,
    234,
    236,
    238
  ],
  "177": [
    158,
    165,
    172,
    175,
    176,
    233,
    234,
    236
  ],
  "178": [
    1,
    2,
    3,
    7,
    10,
    12,
    13,
    15,
    21,
    30,
    98,
    107,
    109,
    179,
    196,
    213,
    241,
    242,
    256,
    373,
    410
  ],
  "179": [
    1,
    2,
    30,
    34,
    115,
    159,
    160,
    178,
    180,
    181,
    186,
    190,
    191,
    192,
    193,
    195,
    197,
    202,
    410
  ],
  "180": [
    1,
    10,
    14,
    21,
    115,
    119,
    145,
    178,
    241,
    242,
    244,
    245,
    410
  ],
  "181": [
    3,
    26,
    159,
    160,
    178,
    179,
    182,
    184,
    188,
    193,
    197
  ],
  "182": [
    1,
    10,
    12,
    13,
    14,
    26,
    114,
    115,
    116,
    117,
    118,
    120,
    144,
    158,
    178,
    179,
    188,
    193,
    194,
    195,
    196,
    198,
    201,
    208,
    209,
    233,
    234,
    236,
    238,
    239,
    256,
    410
  ],
  "183": [
    3,
    7,
    12,
    26,
    116,
    117,
    156,
    159,
    160,
    168,
    178,
    182,
    188,
    194,
    198,
    200,
    201,
    240,
    285,
    288
  ],
  "184": [
    12,
    115,
    119,
    122,
    161,
    162,
    163,
    166,
    178,
    179,
    181,
    195,
    233,
    410
  ],
  "185": [
    181,
    182,
    236
  ],
  "186": [
    1,
    2,
    8,
    30,
    33,
    34,
    178,
    187,
    188,
    190,
    343,
    344,
    345,
    346,
    347,
    380,
    382,
    383,
    385,
    386,
    387,
    389,
    393,
    397,
    398,
    402
  ],
  "187": [
    1,
    2,
    3,
    5,
    108,
    182,
    186,
    188,
    189,
    234,
    235,
    236,
    238,
    239,
    249
  ],
  "188": [
    7,
    11,
    26,
    160,
    182,
    183,
    186,
    187,
    189,
    236,
    239
  ],
  "189": [
    8,
    9,
    30,
    33,
    34,
    108,
    202,
    255,
    342,
    343,
    344,
    345,
    346,
    347,
    373,
    380,
    381,
    384,
    385,
    386,
    393,
    394,
    395,
    398
  ],
  "190": [
    1,
    2,
    3,
    5,
    8,
    11,
    14,
    15,
    16,
    18,
    19,
    20,
    22,
    23,
    24,
    25,
    26,
    30,
    73,
    178,
    179,
    191,
    192,
    256,
    289,
    290,
    291,
    410
  ],
  "191": [
    1,
    2,
    3,
    8,
    30,
    178,
    179,
    190,
    192,
    196,
    304
  ],
  "192": [
    1,
    2,
    30,
    178,
    179,
    190,
    191,
    196,
    256
  ],
  "193": [
    8,
    11,
    26,
    30,
    178,
    179,
    182,
    184,
    194,
    195,
    213,
    240,
    241,
    242
  ],
  "194": [
    11,
    158,
    183,
    188,
    193,
    195,
    200,
    208,
    234,
    238,
    240
  ],
  "195": [
    11,
    158,
    179,
    181,
    184,
    186,
    193,
    194,
    217,
    240
  ],
  "196": [
    1,
    2,
    3,
    7,
    8,
    9,
    13,
    30,
    33,
    48,
    108,
    109,
    115,
    116,
    125,
    126,
    127,
    128,
    129,
    130,
    131,
    134,
    135,
    136,
    162,
    163,
    164,
    178,
    197,
    202,
    256,
    410
  ],
  "197": [
    1,
    2,
    3,
    8,
    9,
    26,
    30,
    178,
    179,
    182,
    183,
    187,
    194,
    196,
    198,
    200,
    202,
    233,
    234,
    235,
    237,
    238,
    239
  ],
  "198": [
    1,
    10,
    12,
    13,
    26,
    114,
    115,
    116,
    117,
    118,
    120,
    144,
    146,
    158,
    172,
    178,
    182,
    187,
    194,
    196,
    256,
    410
  ],
  "199": [
    1,
    178,
    182,
    197,
    198,
    209,
    233,
    234,
    236,
    238,
    239,
    241,
    242
  ],
  "200": [
    3,
    7,
    12,
    116,
    117,
    156,
    159,
    160,
    168,
    178,
    182,
    183,
    197,
    198,
    201,
    240,
    285,
    288
  ],
  "201": [
    182,
    188,
    233,
    236,
    239
  ],
  "202": [
    1,
    2,
    10,
    12,
    30,
    115,
    122,
    126,
    128,
    129,
    130,
    131,
    132,
    133,
    134,
    135,
    136,
    145,
    153,
    162,
    163,
    164,
    178,
    179,
    186,
    190,
    193,
    195,
    196,
    197,
    203,
    204,
    255,
    256,
    257,
    258,
    272,
    275,
    276,
    297,
    305,
    409,
    410,
    411
  ],
  "203": [
    24,
    115,
    125,
    126,
    127,
    128,
    129,
    130,
    131,
    132,
    133,
    134,
    135,
    136,
    179,
    196,
    202,
    275
  ],
  "204": [
    125,
    126,
    127,
    128,
    129,
    130,
    131,
    132,
    133,
    134,
    135,
    136,
    145,
    179,
    196,
    202,
    298
  ],
  "205": [
    11,
    12,
    26,
    27,
    28,
    141,
    142,
    144,
    146,
    148,
    158,
    166,
    171,
    172,
    182,
    188,
    194,
    198,
    206,
    207,
    208,
    209,
    210,
    211,
    212,
    233,
    234,
    237,
    239,
    266,
    278,
    284,
    335
  ],
  "206": [
    12,
    158,
    172,
    205,
    207,
    208,
    232,
    233,
    234,
    235,
    236,
    237,
    238,
    239,
    240
  ],
  "207": [
    5,
    26,
    27,
    141,
    142,
    144,
    165,
    182,
    194,
    199,
    205,
    206,
    215,
    221,
    232,
    234,
    238,
    249
  ],
  "208": [
    11,
    12,
    26,
    27,
    28,
    141,
    142,
    144,
    146,
    148,
    158,
    166,
    171,
    172,
    182,
    188,
    194,
    198,
    205,
    206,
    207,
    209,
    212,
    233,
    234,
    266,
    278,
    282,
    284,
    285,
    298
  ],
  "209": [
    11,
    26,
    30,
    146,
    147,
    148,
    149,
    166,
    167,
    210,
    211,
    234,
    236,
    238,
    266,
    278,
    282,
    284,
    285,
    287
  ],
  "210": [
    1,
    2,
    8,
    11,
    14,
    26,
    30,
    72,
    79,
    147,
    190,
    206,
    208,
    209,
    211,
    270,
    278,
    283,
    290,
    296,
    298,
    304
  ],
  "211": [
    2,
    11,
    26,
    30,
    190,
    206,
    208,
    209,
    210,
    283,
    290,
    296,
    298,
    304
  ],
  "212": [
    146,
    148,
    166,
    182,
    188,
    194,
    209,
    236,
    238,
    266,
    278,
    284,
    285
  ],
  "213": [
    1,
    7,
    12,
    92,
    193,
    214,
    215,
    216,
    217,
    218,
    225,
    229,
    232,
    233,
    235,
    241,
    242,
    348
  ],
  "214": [
    12,
    158,
    163,
    172,
    182,
    213,
    215,
    216,
    217,
    220,
    227,
    230,
    411
  ],
  "215": [
    92,
    94,
    167,
    182,
    194,
    207,
    213,
    214,
    216,
    217,
    221,
    227,
    233,
    234,
    235,
    236,
    238,
    239
  ],
  "216": [
    183,
    188,
    194,
    206,
    213,
    214,
    215,
    217,
    219,
    227,
    228,
    233,
    236,
    239
  ],
  "217": [
    1,
    7,
    12,
    158,
    172,
    193,
    213,
    214,
    215,
    216,
    224,
    241,
    298,
    306,
    316,
    319,
    329,
    346,
    348,
    373,
    378,
    386,
    390
  ],
  "218": [
    1,
    3,
    8,
    10,
    13,
    14,
    20,
    107,
    109,
    161,
    178,
    219,
    220,
    221,
    222,
    223,
    224,
    256,
    373,
    374,
    410
  ],
  "219": [
    151,
    158,
    218,
    220,
    222,
    224,
    256,
    410
  ],
  "220": [
    146,
    148,
    158,
    161,
    218,
    219,
    221,
    222,
    224,
    234,
    242,
    256,
    410
  ],
  "221": [
    149,
    218,
    219,
    220,
    222,
    236,
    239,
    242,
    256,
    410
  ],
  "222": [
    13,
    14,
    24,
    73,
    74,
    115,
    122,
    125,
    128,
    130,
    132,
    134,
    135,
    136,
    137,
    145,
    162,
    196,
    202,
    218,
    223,
    225,
    237,
    256,
    410
  ],
  "223": [
    218,
    222,
    237,
    256,
    410
  ],
  "224": [
    11,
    158,
    161,
    219,
    220,
    222,
    241,
    242
  ],
  "225": [
    7,
    12,
    92,
    108,
    178,
    179,
    180,
    193,
    213,
    218,
    226,
    227,
    228,
    229,
    235,
    269
  ],
  "226": [
    179,
    213,
    218,
    225,
    227,
    228,
    229,
    235,
    236,
    237,
    239
  ],
  "227": [
    7,
    12,
    158,
    163,
    182,
    193,
    195,
    206,
    214,
    218,
    220,
    225,
    226,
    228,
    230,
    233,
    234,
    236,
    271,
    411
  ],
  "228": [
    183,
    194,
    206,
    216,
    219,
    225,
    226,
    227,
    233
  ],
  "229": [
    158,
    225,
    230,
    231
  ],
  "230": [
    158,
    172,
    182,
    213,
    229,
    231,
    233,
    234,
    236,
    239
  ],
  "231": [
    12,
    25,
    125,
    128,
    130,
    132,
    134,
    135,
    162,
    163,
    179,
    180,
    213,
    225,
    229,
    230,
    237,
    241,
    242,
    333
  ],
  "232": [
    8,
    12,
    18,
    20,
    26,
    39,
    108,
    115,
    145,
    165,
    178,
    179,
    180,
    196,
    205,
    209,
    213,
    218,
    225,
    229,
    241,
    242,
    270,
    274,
    277,
    281,
    283,
    410
  ],
  "233": [
    26,
    144,
    149,
    156,
    167,
    168,
    172,
    176,
    177,
    182,
    183,
    184,
    187,
    188,
    194,
    195,
    199,
    200,
    206,
    207,
    214,
    215,
    216,
    219,
    220,
    221,
    227,
    228,
    230,
    232,
    234,
    235,
    236,
    237,
    238,
    239,
    240,
    285,
    287,
    288,
    329,
    332
  ],
  "234": [
    5,
    10,
    26,
    108,
    141,
    142,
    144,
    148,
    167,
    176,
    182,
    187,
    194,
    199,
    207,
    208,
    215,
    221,
    227,
    230,
    236,
    239,
    244,
    247,
    249,
    253,
    274,
    285,
    287
  ],
  "235": [
    26,
    144,
    213,
    218,
    225,
    232,
    233,
    234,
    236,
    237,
    238,
    239,
    240
  ],
  "236": [
    146,
    148,
    166,
    176,
    182,
    188,
    194,
    198,
    206,
    214,
    220,
    227,
    230,
    232,
    233,
    234,
    235,
    237,
    238,
    239,
    240,
    266,
    274,
    278,
    279,
    282,
    283,
    284,
    285
  ],
  "237": [
    112,
    113,
    123,
    222,
    232,
    233,
    234,
    235,
    236,
    238,
    239,
    240
  ],
  "238": [
    4,
    21,
    146,
    148,
    166,
    182,
    188,
    194,
    198,
    209,
    212,
    234,
    235,
    236,
    237,
    239,
    240,
    245,
    251,
    266,
    279,
    282,
    283,
    284,
    285,
    410
  ],
  "239": [
    38,
    158,
    233,
    234,
    235,
    236,
    339
  ],
  "240": [
    11,
    26,
    146,
    148,
    150,
    156,
    166,
    168,
    171,
    182,
    183,
    188,
    197,
    198,
    200,
    233,
    266,
    274,
    278,
    279,
    282,
    283,
    285,
    286,
    288
  ],
  "241": [
    7,
    11,
    18,
    20,
    26,
    35,
    68,
    145,
    158,
    165,
    179,
    193,
    205,
    213,
    218,
    224,
    225,
    229,
    231,
    242,
    270,
    274,
    278,
    279,
    281,
    283,
    290,
    309,
    316,
    320,
    321,
    332,
    343,
    345,
    351,
    352,
    361,
    363,
    374,
    378
  ],
  "242": [
    5,
    11,
    18,
    20,
    26,
    106,
    145,
    162,
    163,
    165,
    172,
    179,
    202,
    205,
    213,
    215,
    217,
    218,
    221,
    222,
    224,
    225,
    229,
    231,
    233,
    234,
    235,
    236,
    237,
    238,
    239,
    240,
    241,
    270,
    274,
    277,
    281,
    283,
    290,
    309,
    329,
    345,
    361,
    363,
    378
  ],
  "243": [
    10,
    11,
    160,
    172,
    244,
    245,
    246,
    247,
    250,
    254,
    268
  ],
  "244": [
    3,
    7,
    9,
    10,
    108,
    137,
    140,
    172,
    243,
    251,
    261,
    262,
    263,
    298,
    360,
    378,
    391,
    410
  ],
  "245": [
    14,
    26,
    120,
    144,
    160,
    172,
    179,
    180,
    243,
    244,
    246,
    250
  ],
  "246": [
    10,
    172,
    254
  ],
  "247": [
    141,
    160,
    172,
    234,
    245,
    253
  ],
  "248": [
    172
  ],
  "249": [
    13,
    14,
    106,
    108,
    142,
    256,
    410
  ],
  "250": [
    160,
    172
  ],
  "251": [
    9,
    21,
    23,
    110,
    114,
    160,
    172,
    238,
    245,
    252,
    253,
    254,
    298,
    321
  ],
  "252": [
    9,
    110,
    137,
    139,
    160,
    172,
    246,
    251,
    254,
    298
  ],
  "253": [
    23,
    141,
    142,
    147,
    160,
    172,
    234,
    238,
    251,
    252,
    298,
    321
  ],
  "254": [
    10,
    28,
    108,
    110,
    137,
    139,
    172,
    244,
    246,
    251,
    252
  ],
  "255": [
    1,
    7,
    9,
    10,
    11,
    16,
    20,
    30,
    32,
    33,
    41,
    78,
    99,
    108,
    109,
    158,
    172,
    174,
    202,
    244,
    256,
    257,
    258,
    259,
    265,
    311,
    318,
    342,
    348,
    349,
    409,
    410
  ],
  "256": [
    13,
    158,
    196,
    202,
    255,
    257,
    258,
    259,
    410
  ],
  "257": [
    158,
    256,
    259,
    265,
    266,
    410
  ],
  "258": [
    10,
    158,
    164,
    172,
    202,
    255,
    256,
    257,
    259
  ],
  "259": [
    11,
    256,
    257,
    258
  ],
  "260": [
    158,
    172,
    257,
    259
  ],
  "261": [
    1,
    9,
    10,
    108,
    172,
    244,
    262,
    263,
    264,
    270,
    377,
    394
  ],
  "262": [
    108,
    124,
    172,
    261,
    263,
    264,
    298,
    349,
    357
  ],
  "263": [
    8,
    9,
    10,
    12,
    137,
    243,
    244,
    261,
    262,
    264,
    298,
    306,
    311,
    342
  ],
  "264": [
    9,
    30,
    33,
    261,
    262,
    263,
    265,
    298,
    306,
    348,
    349,
    377
  ],
  "265": [
    8,
    30,
    255,
    257,
    264,
    266,
    304,
    377,
    410
  ],
  "266": [
    209,
    240,
    257,
    410
  ],
  "267": [
    10,
    261,
    268
  ],
  "268": [
    243,
    244,
    267,
    299,
    348
  ],
  "269": [
    1,
    3,
    7,
    12,
    18,
    19,
    20,
    35,
    83,
    141,
    144,
    158,
    241,
    242,
    270,
    271,
    272,
    273,
    274,
    275,
    276,
    277,
    278,
    279,
    280,
    281,
    282,
    283,
    284,
    289,
    290,
    297,
    330,
    355
  ],
  "270": [
    1,
    2,
    14,
    30,
    196,
    237,
    241,
    269,
    271,
    272,
    273,
    274,
    275,
    276,
    280,
    290,
    292,
    305
  ],
  "271": [
    1,
    145,
    146,
    148,
    158,
    162,
    163,
    164,
    174,
    262,
    269,
    270,
    272,
    273,
    274,
    275,
    276,
    280,
    281,
    282,
    289,
    292,
    297,
    299,
    300,
    301,
    302,
    303,
    304,
    305,
    323,
    340,
    411
  ],
  "272": [
    1,
    2,
    9,
    12,
    30,
    92,
    122,
    145,
    163,
    178,
    190,
    213,
    218,
    225,
    234,
    235,
    236,
    237,
    238,
    239,
    269,
    270,
    271,
    273,
    274,
    275,
    276,
    277,
    278,
    279,
    280,
    281,
    282,
    283,
    284,
    285,
    286,
    287,
    289,
    290,
    296,
    297,
    298,
    299,
    300,
    301,
    302,
    303,
    304,
    305,
    323,
    341,
    361,
    363
  ],
  "273": [
    269,
    270,
    272,
    274,
    280,
    302,
    303
  ],
  "274": [
    1,
    240,
    269,
    270,
    271,
    272,
    273,
    275,
    276,
    277,
    278,
    279
  ],
  "275": [
    11,
    164,
    196,
    198,
    202,
    241,
    242,
    269,
    270,
    271,
    272,
    273,
    274,
    276,
    277,
    278,
    279,
    280,
    281,
    282,
    283,
    284,
    289,
    290,
    292,
    300,
    301,
    302,
    303,
    304,
    305,
    410,
    411
  ],
  "276": [
    1,
    145,
    174,
    269,
    270,
    271,
    272,
    273,
    274,
    275,
    297,
    410
  ],
  "277": [
    1,
    213,
    233,
    234,
    238,
    241,
    269,
    272,
    276,
    278,
    279,
    285,
    287,
    288,
    297,
    299,
    321,
    410
  ],
  "278": [
    2,
    11,
    26,
    30,
    144,
    275,
    282,
    284,
    410
  ],
  "279": [
    145,
    234,
    235,
    236,
    237,
    238,
    239,
    240,
    269,
    272,
    274,
    277,
    281,
    283,
    285,
    286
  ],
  "280": [
    1,
    5,
    11,
    98,
    233,
    269,
    272,
    281,
    282,
    283,
    297,
    301,
    305,
    306
  ],
  "281": [
    1,
    213,
    233,
    234,
    238,
    241,
    269,
    272,
    276,
    280,
    282,
    285,
    287,
    288,
    297
  ],
  "282": [
    5,
    11,
    26,
    27,
    144,
    202,
    208,
    234,
    236,
    238,
    239,
    240,
    242,
    269,
    275,
    278,
    284,
    287,
    288
  ],
  "283": [
    1,
    213,
    233,
    234,
    238,
    241,
    269,
    272,
    276,
    284,
    285,
    287,
    288,
    297,
    299,
    410
  ],
  "284": [
    5,
    26,
    27,
    30,
    144,
    202,
    208,
    234,
    236,
    238,
    239,
    240,
    242,
    269,
    275,
    283,
    287,
    288,
    289,
    290
  ],
  "285": [
    5,
    108,
    208,
    234,
    236,
    238,
    240,
    249,
    269,
    272,
    277,
    281,
    283,
    286,
    290
  ],
  "286": [
    169,
    208,
    234,
    236,
    238,
    239,
    240,
    269,
    274,
    277,
    281,
    283,
    285,
    290
  ],
  "287": [
    5,
    11,
    26,
    144,
    209,
    234,
    238,
    272,
    277,
    281,
    283,
    285,
    286,
    288,
    296
  ],
  "288": [
    1,
    11,
    26,
    28,
    114,
    156,
    168,
    183,
    188,
    194,
    200,
    239,
    240,
    285,
    287
  ],
  "289": [
    1,
    2,
    3,
    5,
    8,
    11,
    14,
    21,
    26,
    30,
    31,
    32,
    71,
    98,
    190,
    191,
    192,
    210,
    211,
    269,
    270,
    273,
    290,
    291,
    292,
    293,
    294,
    295,
    296,
    304,
    306,
    307,
    311,
    352,
    353,
    374,
    385,
    393,
    403
  ],
  "290": [
    2,
    5,
    11,
    26,
    30,
    32,
    80,
    190,
    191,
    192,
    210,
    211,
    269,
    270,
    284,
    289,
    291,
    292,
    293,
    294,
    295,
    296,
    304,
    319,
    352,
    385,
    394,
    403
  ],
  "291": [
    2,
    30,
    269,
    280,
    289,
    290,
    293,
    294,
    295,
    296,
    301,
    303,
    393,
    394,
    403
  ],
  "292": [
    2,
    8,
    11,
    26,
    30,
    190,
    211,
    289,
    290,
    296,
    304
  ],
  "293": [
    1,
    2,
    11,
    26,
    30,
    31,
    146,
    269,
    270,
    273,
    276,
    284,
    289,
    290,
    291,
    292,
    294,
    295,
    296,
    304,
    393
  ],
  "294": [
    2,
    3,
    11,
    30,
    100,
    218,
    269,
    270,
    284,
    289,
    290,
    291,
    293,
    295,
    303,
    304,
    394,
    395
  ],
  "295": [
    2,
    30,
    269,
    270,
    276,
    280,
    289,
    290,
    291,
    293,
    294,
    296,
    301
  ],
  "296": [
    1,
    2,
    11,
    21,
    26,
    30,
    190,
    191,
    192,
    211,
    289,
    290,
    292,
    293,
    295,
    303,
    304
  ],
  "297": [
    1,
    2,
    12,
    30,
    269,
    270,
    274,
    275,
    276,
    277,
    280,
    283,
    285,
    287,
    289,
    298,
    299,
    300,
    301,
    302,
    303,
    304,
    305
  ],
  "298": [
    1,
    7,
    8,
    9,
    10,
    12,
    13,
    15,
    16,
    17,
    18,
    19,
    20,
    21,
    26,
    27,
    28,
    29,
    30,
    33,
    34,
    35,
    36,
    37,
    38,
    39,
    40,
    41,
    42,
    45,
    46,
    47,
    48,
    49,
    56,
    57,
    75,
    76,
    77,
    78,
    79,
    80,
    81,
    82,
    83,
    84,
    85,
    86,
    87,
    88,
    89,
    90,
    91,
    92,
    93,
    94,
    95,
    96,
    97,
    98,
    99,
    100,
    101,
    103,
    106,
    107,
    108,
    112,
    124,
    135,
    137,
    141,
    142,
    143,
    144,
    145,
    146,
    148,
    158,
    159,
    162,
    163,
    166,
    172,
    174,
    178,
    179,
    182,
    188,
    189,
    190,
    194,
    198,
    205,
    208,
    231,
    234,
    237,
    241,
    244,
    248,
    251,
    252,
    255,
    257,
    262,
    263,
    264,
    265,
    266,
    269,
    270,
    271,
    272,
    274,
    275,
    276,
    278,
    282,
    284,
    285,
    297,
    299,
    300,
    301,
    302,
    303,
    304,
    305,
    306,
    309,
    311,
    312,
    313,
    316,
    318,
    319,
    320,
    321,
    322,
    323,
    326,
    327,
    328,
    330,
    331,
    332,
    333,
    334,
    337,
    339,
    341,
    342,
    343,
    344,
    345,
    346,
    347,
    348,
    349,
    350,
    351,
    352,
    353,
    354,
    355,
    356,
    359,
    360,
    361,
    363,
    370,
    372,
    373,
    374,
    375,
    376,
    377,
    378,
    379,
    380,
    381,
    383,
    384,
    385,
    386,
    387,
    388,
    389,
    390,
    393,
    394,
    395,
    396,
    397,
    398,
    401,
    402,
    403,
    405,
    406,
    407,
    408,
    409,
    410
  ],
  "299": [
    1,
    8,
    9,
    10,
    13,
    16,
    17,
    18,
    19,
    20,
    26,
    30,
    33,
    34,
    35,
    36,
    37,
    38,
    39,
    40,
    41,
    42,
    47,
    77,
    78,
    79,
    80,
    81,
    82,
    83,
    84,
    85,
    86,
    87,
    88,
    89,
    90,
    91,
    92,
    93,
    94,
    95,
    96,
    97,
    98,
    103,
    108,
    145,
    172,
    174,
    189,
    190,
    208,
    213,
    217,
    241,
    251,
    255,
    265,
    268,
    269,
    270,
    271,
    272,
    274,
    275,
    276,
    277,
    278,
    280,
    281,
    282,
    283,
    284,
    285,
    289,
    296,
    297,
    298,
    302,
    304,
    309,
    312,
    321,
    323,
    342,
    344,
    345,
    346,
    347,
    348,
    349,
    351,
    373,
    374,
    375,
    376,
    377,
    378,
    379,
    381,
    386,
    387,
    389,
    390,
    397,
    407
  ],
  "300": [
    1,
    8,
    9,
    11,
    14,
    15,
    16,
    20,
    26,
    45,
    46,
    47,
    48,
    49,
    54,
    56,
    57,
    58,
    59,
    60,
    61,
    65,
    67,
    68,
    70,
    71,
    75,
    76,
    80,
    98,
    99,
    100,
    101,
    104,
    105,
    158,
    159,
    172,
    205,
    237,
    240,
    241,
    262,
    269,
    270,
    271,
    272,
    274,
    275,
    276,
    277,
    278,
    297,
    298,
    299,
    302,
    303,
    304,
    305,
    306,
    308,
    309,
    311,
    312,
    313,
    316,
    317,
    318,
    320,
    321,
    323,
    330,
    331,
    332,
    333,
    337,
    339,
    340,
    341,
    348,
    349,
    351,
    359,
    360,
    361,
    363,
    365,
    366,
    367,
    368,
    378,
    389,
    397,
    401,
    402,
    406,
    407,
    408,
    409
  ],
  "301": [
    1,
    2,
    30,
    269,
    270,
    276,
    280,
    289,
    295,
    297,
    299,
    305
  ],
  "302": [
    1,
    8,
    9,
    11,
    13,
    14,
    15,
    16,
    17,
    18,
    19,
    20,
    26,
    30,
    33,
    34,
    45,
    46,
    47,
    48,
    49,
    54,
    56,
    57,
    58,
    59,
    60,
    61,
    65,
    67,
    68,
    70,
    71,
    75,
    76,
    80,
    98,
    99,
    100,
    101,
    104,
    105,
    108,
    158,
    189,
    205,
    237,
    240,
    241,
    251,
    262,
    269,
    270,
    271,
    272,
    275,
    276,
    280,
    283,
    284,
    294,
    295,
    297,
    298,
    299,
    300,
    303,
    304,
    305,
    306,
    307,
    309,
    311,
    312,
    313,
    316,
    317,
    318,
    321,
    323,
    330,
    331,
    332,
    333,
    337,
    339,
    341,
    342,
    344,
    345,
    346,
    347,
    348,
    349,
    352,
    359,
    360,
    361,
    363,
    365,
    366,
    367,
    369,
    378,
    380,
    381,
    385,
    389,
    401,
    402,
    405,
    406,
    407,
    408
  ],
  "303": [
    1,
    2,
    30,
    269,
    270,
    289,
    290,
    291,
    292,
    293,
    294,
    295,
    296,
    305
  ],
  "304": [
    1,
    2,
    3,
    5,
    8,
    9,
    10,
    11,
    15,
    17,
    18,
    19,
    20,
    21,
    26,
    30,
    31,
    32,
    33,
    34,
    37,
    40,
    41,
    42,
    77,
    78,
    79,
    80,
    81,
    82,
    83,
    84,
    85,
    86,
    87,
    88,
    89,
    90,
    91,
    92,
    93,
    94,
    95,
    96,
    97,
    98,
    99,
    100,
    101,
    103,
    104,
    105,
    108,
    119,
    124,
    135,
    145,
    172,
    174,
    178,
    179,
    187,
    189,
    190,
    191,
    192,
    202,
    213,
    217,
    255,
    269,
    270,
    271,
    272,
    275,
    276,
    289,
    290,
    291,
    292,
    293,
    294,
    295,
    296,
    297,
    298,
    299,
    300,
    302,
    303,
    306,
    307,
    309,
    311,
    312,
    318,
    321,
    323,
    337,
    339,
    342,
    343,
    345,
    346,
    347,
    348,
    349,
    352,
    354,
    369,
    373,
    375,
    380,
    381,
    383,
    385,
    386,
    388,
    389,
    390,
    391,
    402,
    405,
    406,
    407,
    409
  ],
  "305": [
    1,
    12,
    30,
    269,
    270,
    274,
    275,
    276,
    277,
    280,
    283,
    289,
    297,
    298,
    299,
    300,
    301,
    302,
    303,
    304,
    321,
    323
  ],
  "306": [
    1,
    2,
    8,
    9,
    20,
    30,
    39,
    47,
    52,
    54,
    80,
    198,
    218,
    241,
    270,
    298,
    300,
    302,
    307,
    309,
    310,
    311,
    312,
    313,
    314,
    316,
    318,
    330,
    334,
    335,
    336,
    351,
    362,
    363,
    378,
    405,
    406
  ],
  "307": [
    1,
    2,
    8,
    30,
    47,
    56,
    306,
    311,
    313,
    336,
    393,
    394,
    405
  ],
  "308": [
    8,
    9,
    14,
    20,
    39,
    47,
    52,
    56,
    218,
    241,
    306,
    311,
    312,
    314,
    318,
    325,
    330,
    334,
    351,
    362,
    378
  ],
  "309": [
    3,
    7,
    9,
    15,
    16,
    17,
    18,
    19,
    20,
    158,
    159,
    172,
    213,
    229,
    241,
    242,
    255,
    298,
    299,
    300,
    302,
    304,
    306,
    311,
    313,
    314,
    316,
    317,
    320,
    321,
    327,
    330,
    332,
    339,
    348,
    349,
    351,
    357,
    361,
    363,
    370,
    372,
    373,
    374,
    378,
    404,
    405
  ],
  "310": [
    20,
    55,
    306,
    330,
    335,
    351,
    369,
    370,
    378,
    406
  ],
  "311": [
    1,
    2,
    8,
    16,
    18,
    30,
    33,
    47,
    52,
    56,
    103,
    172,
    178,
    189,
    298,
    300,
    302,
    304,
    306,
    307,
    308,
    312,
    313,
    315,
    316,
    319,
    336,
    349,
    351,
    355,
    356,
    357,
    359,
    369,
    378,
    381,
    391,
    393,
    396,
    397,
    401,
    405
  ],
  "312": [
    8,
    9,
    14,
    16,
    17,
    18,
    19,
    20,
    33,
    46,
    75,
    108,
    299,
    306,
    308,
    311,
    313,
    316,
    318,
    320,
    321,
    337,
    342,
    405
  ],
  "313": [
    8,
    9,
    11,
    14,
    15,
    16,
    17,
    18,
    19,
    20,
    22,
    26,
    30,
    33,
    45,
    46,
    47,
    48,
    52,
    54,
    56,
    59,
    61,
    68,
    71,
    74,
    75,
    76,
    80,
    172,
    255,
    298,
    300,
    302,
    304,
    306,
    307,
    309,
    311,
    312,
    316,
    318,
    319,
    321,
    330,
    334,
    336,
    338,
    351,
    353,
    373,
    378,
    391,
    395,
    402,
    406,
    407,
    410
  ],
  "314": [
    8,
    16,
    17,
    18,
    19,
    20,
    41,
    75,
    107,
    142,
    309,
    311,
    312,
    316,
    318,
    351
  ],
  "315": [
    11,
    46,
    56,
    196,
    311,
    312,
    349,
    393,
    394,
    397,
    398,
    399
  ],
  "316": [
    1,
    2,
    8,
    9,
    12,
    16,
    17,
    18,
    19,
    20,
    30,
    37,
    47,
    55,
    76,
    77,
    80,
    103,
    158,
    159,
    172,
    241,
    242,
    255,
    297,
    298,
    299,
    300,
    302,
    304,
    306,
    309,
    311,
    312,
    313,
    314,
    317,
    318,
    319,
    320,
    321,
    330,
    334,
    339,
    345,
    351,
    355,
    356,
    365,
    366,
    367,
    369,
    370,
    378,
    386,
    406,
    407
  ],
  "317": [
    7,
    11,
    26,
    241,
    242,
    298,
    300,
    302,
    304,
    306,
    311,
    316,
    321
  ],
  "318": [
    16,
    17,
    18,
    19,
    20,
    37,
    38,
    45,
    47,
    48,
    52,
    55,
    59,
    71,
    77,
    217,
    218,
    241,
    255,
    298,
    299,
    300,
    302,
    304,
    306,
    307,
    308,
    309,
    310,
    311,
    313,
    314,
    316,
    319,
    320,
    321,
    326,
    330,
    334,
    336,
    337,
    345,
    367,
    370,
    379,
    386,
    395,
    406,
    407
  ],
  "319": [
    8,
    9,
    30,
    33,
    306,
    311,
    312,
    313,
    316,
    321,
    323,
    342,
    346,
    349,
    351,
    352,
    353,
    354,
    355,
    356,
    363,
    372
  ],
  "320": [
    1,
    9,
    172,
    174,
    244,
    255,
    265,
    298,
    299,
    300,
    304,
    316,
    318,
    330,
    334,
    351,
    366,
    377,
    407
  ],
  "321": [
    16,
    17,
    18,
    19,
    26,
    35,
    37,
    77,
    145,
    158,
    159,
    162,
    172,
    175,
    231,
    241,
    242,
    246,
    252,
    272,
    305,
    306,
    313,
    316,
    318,
    320,
    322,
    323,
    324,
    325,
    339,
    341,
    405
  ],
  "322": [
    92,
    158,
    159,
    298,
    321,
    323,
    341
  ],
  "323": [
    1,
    8,
    13,
    14,
    76,
    108,
    145,
    232,
    270,
    272,
    298,
    299,
    300,
    302,
    303,
    304,
    306,
    321,
    341
  ],
  "324": [
    112,
    233,
    235,
    256,
    325
  ],
  "325": [
    47,
    316,
    318,
    321
  ],
  "326": [
    298,
    328
  ],
  "327": [
    130,
    159,
    172,
    213,
    298,
    326,
    328,
    329
  ],
  "328": [
    306,
    311,
    312,
    313,
    318,
    326,
    327
  ],
  "329": [
    8,
    26,
    158,
    159,
    172,
    213,
    217,
    218,
    232,
    233,
    234,
    235,
    236,
    237,
    239,
    299,
    326,
    327,
    328
  ],
  "330": [
    1,
    8,
    47,
    55,
    306,
    307,
    309,
    310,
    316,
    318,
    331,
    332,
    333,
    334,
    335,
    336,
    405,
    406
  ],
  "331": [
    9,
    316,
    330,
    332,
    334,
    336
  ],
  "332": [
    159,
    172,
    330,
    331
  ],
  "333": [
    112,
    123,
    142,
    324,
    325,
    332
  ],
  "334": [
    1,
    8,
    9,
    47,
    48,
    52,
    78,
    90,
    93,
    94,
    103,
    255,
    298,
    299,
    300,
    302,
    304,
    306,
    308,
    310,
    313,
    316,
    318,
    319,
    320,
    321,
    330,
    335,
    336,
    337,
    338,
    405,
    406,
    407,
    408
  ],
  "335": [
    20,
    55,
    208,
    306,
    309,
    310,
    330,
    378,
    406
  ],
  "336": [
    2,
    30,
    47,
    306,
    307,
    311,
    330
  ],
  "337": [
    1,
    2,
    9,
    33,
    98,
    100,
    108,
    298,
    299,
    300,
    302,
    304,
    306,
    311,
    312,
    316,
    334,
    342,
    346,
    380,
    384,
    385,
    405,
    406
  ],
  "338": [
    8,
    46,
    48,
    313,
    316,
    334
  ],
  "339": [
    3,
    7,
    9,
    13,
    22,
    25,
    30,
    32,
    48,
    51,
    52,
    99,
    100,
    108,
    111,
    112,
    119,
    135,
    137,
    151,
    158,
    159,
    172,
    231,
    255,
    267,
    297,
    298,
    300,
    302,
    304,
    306,
    316,
    321,
    340,
    341,
    346,
    347,
    349,
    359,
    361,
    372,
    374,
    381,
    385,
    394
  ],
  "340": [
    92,
    145,
    158,
    159,
    160,
    172,
    178,
    195,
    300,
    302,
    304,
    321,
    323,
    339,
    341
  ],
  "341": [
    17,
    18,
    45,
    60,
    158,
    159,
    269,
    298,
    299,
    300,
    319,
    322,
    323,
    339,
    340,
    348,
    349,
    351,
    368,
    372,
    390
  ],
  "342": [
    1,
    8,
    9,
    30,
    33,
    34,
    80,
    108,
    124,
    135,
    158,
    189,
    255,
    264,
    298,
    299,
    302,
    304,
    311,
    312,
    313,
    316,
    319,
    343,
    344,
    345,
    346,
    347,
    348,
    349,
    354,
    358,
    359,
    360,
    369,
    373,
    374,
    375,
    378,
    380,
    381,
    405,
    407
  ],
  "343": [
    1,
    8,
    9,
    11,
    15,
    16,
    18,
    19,
    30,
    33,
    80,
    108,
    124,
    135,
    189,
    255,
    264,
    298,
    299,
    302,
    304,
    311,
    312,
    313,
    316,
    319,
    344,
    345,
    346,
    347,
    348,
    349,
    354,
    358,
    359,
    360,
    369,
    373,
    374,
    375,
    378,
    380,
    381,
    405,
    407
  ],
  "344": [
    8,
    9,
    10,
    15,
    18,
    19,
    30,
    33,
    34,
    37,
    80,
    103,
    124,
    255,
    256,
    298,
    299,
    306,
    311,
    312,
    316,
    319,
    342,
    343,
    345,
    346,
    347,
    348,
    352,
    378,
    379,
    380,
    407,
    409
  ],
  "345": [
    8,
    9,
    30,
    33,
    34,
    108,
    135,
    224,
    241,
    242,
    270,
    298,
    299,
    302,
    306,
    309,
    311,
    312,
    313,
    316,
    317,
    318,
    319,
    342,
    343,
    344,
    351,
    354,
    355,
    380,
    381,
    382,
    383,
    384,
    385,
    386,
    390,
    391
  ],
  "346": [
    1,
    3,
    8,
    9,
    16,
    19,
    30,
    33,
    108,
    124,
    158,
    189,
    264,
    298,
    302,
    304,
    309,
    311,
    312,
    313,
    316,
    319,
    342,
    343,
    344,
    345,
    348,
    349,
    351,
    352,
    353,
    354,
    355,
    356,
    357,
    358,
    359,
    369,
    373,
    374,
    376,
    380,
    381,
    384,
    385,
    386,
    390
  ],
  "347": [
    8,
    9,
    11,
    15,
    16,
    18,
    19,
    28,
    30,
    33,
    103,
    108,
    110,
    112,
    113,
    124,
    132,
    135,
    189,
    191,
    231,
    241,
    242,
    298,
    299,
    311,
    312,
    316,
    342,
    343,
    344,
    345,
    346,
    348,
    349,
    351,
    352,
    354,
    356,
    380,
    381,
    384,
    385,
    386,
    390
  ],
  "348": [
    1,
    8,
    9,
    16,
    19,
    30,
    33,
    108,
    124,
    158,
    189,
    264,
    298,
    302,
    304,
    306,
    309,
    311,
    312,
    313,
    316,
    319,
    342,
    345,
    346,
    349,
    351,
    352,
    353,
    354,
    355,
    356,
    357,
    358,
    359,
    369,
    373,
    374,
    376,
    380,
    381,
    384,
    385,
    386
  ],
  "349": [
    1,
    8,
    9,
    16,
    19,
    30,
    33,
    108,
    124,
    158,
    189,
    264,
    298,
    302,
    304,
    309,
    311,
    313,
    316,
    319,
    342,
    344,
    345,
    348,
    351,
    352,
    353,
    354,
    355,
    356,
    357,
    358,
    359,
    362,
    369,
    372,
    373,
    374,
    376,
    378,
    380,
    381,
    384,
    385,
    386,
    388,
    393,
    394,
    395,
    397,
    398,
    405,
    406,
    407,
    408,
    409
  ],
  "350": [
    108,
    124,
    158,
    189,
    298,
    302,
    304,
    309,
    342,
    348,
    349,
    351,
    352,
    353,
    354,
    355,
    356,
    357,
    358
  ],
  "351": [
    9,
    11,
    30,
    241,
    242,
    300,
    304,
    306,
    307,
    308,
    309,
    310,
    319,
    341,
    348,
    349,
    350,
    352,
    353,
    355,
    356,
    357,
    358,
    359,
    361,
    362,
    369,
    370,
    373,
    374,
    378,
    380,
    381,
    386,
    387
  ],
  "352": [
    2,
    9,
    11,
    30,
    108,
    241,
    242,
    303,
    304,
    309,
    348,
    349,
    350,
    351,
    353,
    354,
    355,
    356,
    357,
    358,
    380
  ],
  "353": [
    9,
    302,
    303,
    304,
    309,
    348,
    349,
    351,
    352,
    380
  ],
  "354": [
    348,
    349,
    351,
    353,
    380
  ],
  "355": [
    9,
    269,
    309,
    311,
    313,
    316,
    319,
    348,
    349,
    351,
    352,
    353,
    356,
    357,
    363,
    372
  ],
  "356": [
    309,
    311,
    313,
    316,
    348,
    349,
    350,
    351,
    352,
    353,
    354,
    355,
    357,
    358,
    373,
    380
  ],
  "357": [
    9,
    108,
    124,
    297,
    309,
    316,
    319,
    348,
    349,
    350,
    351,
    352,
    353,
    356,
    380
  ],
  "358": [
    108,
    124,
    306,
    309,
    348,
    349,
    351,
    352,
    357
  ],
  "359": [
    3,
    7,
    9,
    30,
    108,
    124,
    158,
    264,
    309,
    311,
    313,
    316,
    319,
    342,
    348,
    349,
    351,
    352,
    353,
    354,
    355,
    356,
    357,
    358,
    360,
    361,
    362,
    363,
    364,
    365,
    366,
    367,
    368
  ],
  "360": [
    7,
    108,
    298,
    359,
    361,
    363,
    365,
    366,
    367,
    378,
    379
  ],
  "361": [
    359,
    360,
    362,
    363,
    364
  ],
  "362": [
    158,
    351,
    359,
    360,
    361,
    363
  ],
  "363": [
    8,
    9,
    309,
    311,
    312,
    313,
    316,
    319,
    320,
    348,
    349,
    351,
    356,
    357,
    359,
    360,
    361,
    362,
    365,
    366,
    367
  ],
  "364": [
    255,
    311,
    359,
    360,
    361,
    362,
    366,
    367
  ],
  "365": [
    309,
    311,
    312,
    316,
    319,
    320,
    348,
    349,
    359,
    360,
    361,
    362,
    363,
    364,
    366,
    367
  ],
  "366": [
    2,
    7,
    9,
    11,
    14,
    30,
    241,
    255,
    320,
    348,
    349,
    357,
    359,
    360,
    361,
    362,
    363,
    364
  ],
  "367": [
    9,
    33,
    196,
    306,
    309,
    311,
    312,
    313,
    316,
    342,
    343,
    344,
    345,
    346,
    347,
    348,
    349,
    359,
    360,
    363
  ],
  "368": [
    1,
    2,
    9,
    30,
    269,
    276,
    277,
    280,
    300,
    311,
    341,
    349,
    365,
    367
  ],
  "369": [
    8,
    9,
    33,
    124,
    298,
    306,
    308,
    309,
    310,
    311,
    312,
    316,
    319,
    320,
    342,
    344,
    347,
    348,
    349,
    351,
    352,
    353,
    355,
    357,
    358,
    370,
    371,
    372
  ],
  "370": [
    8,
    9,
    33,
    124,
    298,
    306,
    309,
    311,
    312,
    316,
    319,
    320,
    342,
    344,
    347,
    348,
    349,
    351,
    352,
    353,
    355,
    356,
    357,
    358,
    369,
    371,
    372
  ],
  "371": [
    9,
    30,
    33,
    309,
    312,
    319,
    320,
    348,
    349,
    351,
    352,
    353,
    357,
    358,
    370
  ],
  "372": [
    8,
    9,
    99,
    306,
    309,
    311,
    312,
    316,
    319,
    320,
    342,
    344,
    346,
    347,
    348,
    349,
    351,
    355,
    357,
    358,
    369,
    370,
    371
  ],
  "373": [
    15,
    16,
    17,
    18,
    19,
    20,
    262,
    298,
    299,
    304,
    309,
    348,
    349,
    374,
    377,
    379,
    405
  ],
  "374": [
    2,
    3,
    16,
    20,
    30,
    32,
    33,
    241,
    242,
    309,
    373,
    375,
    377,
    389
  ],
  "375": [
    9,
    16,
    20,
    33,
    241,
    319,
    348,
    349,
    351,
    373,
    374,
    376,
    403,
    405
  ],
  "376": [
    16,
    26,
    33,
    108,
    319,
    373,
    375,
    397
  ],
  "377": [
    10,
    255,
    262,
    263,
    264,
    373,
    374,
    375
  ],
  "378": [
    7,
    9,
    20,
    33,
    56,
    232,
    298,
    299,
    300,
    302,
    304,
    306,
    307,
    308,
    309,
    310,
    311,
    316,
    348,
    351,
    360,
    379
  ],
  "379": [
    9,
    16,
    20,
    75,
    298,
    299,
    300,
    302,
    304,
    348,
    349,
    378
  ],
  "380": [
    8,
    9,
    30,
    33,
    80,
    108,
    189,
    255,
    298,
    304,
    316,
    342,
    348,
    354,
    383
  ],
  "381": [
    9,
    33,
    34,
    100,
    135,
    189,
    255,
    298,
    300,
    302,
    304,
    346,
    351,
    352,
    353,
    382,
    383,
    385,
    407,
    409
  ],
  "382": [
    9,
    30,
    35,
    42,
    100,
    304,
    348,
    349,
    381,
    410
  ],
  "383": [
    33,
    189,
    287,
    311,
    382,
    389
  ],
  "384": [
    2,
    3,
    8,
    9,
    30,
    42,
    79,
    98,
    99,
    103,
    112,
    255,
    298,
    300,
    304,
    311,
    316,
    346,
    348,
    349,
    380,
    381,
    382,
    383,
    392
  ],
  "385": [
    2,
    8,
    9,
    30,
    33,
    80,
    99,
    100,
    108,
    135,
    189,
    190,
    270,
    293,
    296,
    298,
    299,
    300,
    302,
    304,
    312,
    342,
    343,
    346,
    347,
    352,
    373,
    374,
    375,
    378,
    380,
    381,
    386,
    388,
    390,
    391,
    392,
    393
  ],
  "386": [
    9,
    298,
    348,
    349,
    351,
    352,
    353,
    387,
    389,
    398
  ],
  "387": [
    2,
    8,
    9,
    30,
    33,
    297,
    299,
    343,
    380,
    381,
    383,
    386,
    388,
    392
  ],
  "388": [
    30,
    348,
    349,
    352,
    353,
    355,
    386,
    403
  ],
  "389": [
    298,
    349,
    386,
    387
  ],
  "390": [
    2,
    8,
    9,
    30,
    31,
    33,
    186,
    261,
    264,
    269,
    280,
    289,
    319,
    342,
    343,
    346,
    348,
    349,
    352,
    373,
    374,
    375,
    376,
    377,
    380,
    381,
    382,
    385,
    386,
    387,
    388,
    391,
    392,
    405
  ],
  "391": [
    8,
    9,
    30,
    31,
    33,
    241,
    269,
    277,
    280,
    289,
    291,
    298,
    299,
    300,
    304,
    306,
    307,
    311,
    313,
    316,
    317,
    318,
    320,
    342,
    343,
    345,
    385,
    386,
    390,
    392
  ],
  "392": [
    2,
    5,
    8,
    9,
    30,
    31,
    33,
    99,
    186,
    190,
    264,
    289,
    290,
    293,
    303,
    304,
    306,
    307,
    316,
    319,
    342,
    343,
    346,
    348,
    349,
    352,
    358,
    373,
    374,
    375,
    376,
    377,
    380,
    381,
    382,
    383,
    384,
    385,
    386,
    387,
    388,
    390,
    391
  ],
  "393": [
    30,
    32,
    56,
    62,
    172,
    298,
    311,
    315,
    349,
    394,
    395,
    396,
    397,
    402,
    403
  ],
  "394": [
    14,
    32,
    56,
    62,
    311,
    315,
    348,
    349,
    380,
    393,
    396,
    397,
    398,
    403
  ],
  "395": [
    15,
    16,
    18,
    19,
    30,
    77,
    196,
    389,
    396,
    397,
    398,
    399,
    400,
    402,
    403,
    405
  ],
  "396": [
    14,
    262,
    298,
    348,
    349,
    393,
    394,
    397,
    398,
    399,
    400
  ],
  "397": [
    2,
    11,
    30,
    56,
    255,
    306,
    311,
    348,
    380,
    393,
    394,
    398,
    399,
    401,
    403,
    405,
    409
  ],
  "398": [
    15,
    30,
    46,
    56,
    189,
    306,
    312,
    314,
    315,
    349,
    393,
    394,
    395,
    396,
    397,
    399,
    401,
    405
  ],
  "399": [
    56,
    298,
    393,
    394,
    395,
    397,
    398,
    401
  ],
  "400": [
    8,
    30,
    306,
    315,
    349,
    393,
    394,
    395,
    396,
    397,
    399,
    401,
    405,
    406,
    407,
    408
  ],
  "401": [
    15,
    30,
    46,
    56,
    189,
    262,
    298,
    300,
    302,
    306,
    312,
    314,
    315,
    349,
    393,
    394,
    395,
    396,
    397,
    398,
    399,
    405
  ],
  "402": [
    8,
    14,
    15,
    16,
    17,
    18,
    19,
    20,
    30,
    270,
    297,
    298,
    299,
    300,
    302,
    303,
    305,
    389,
    395,
    403,
    405
  ],
  "403": [
    2,
    8,
    11,
    30,
    269,
    291,
    343,
    352,
    353,
    394,
    395
  ],
  "404": [
    172,
    298
  ],
  "405": [
    8,
    16,
    30,
    33,
    255,
    318,
    342,
    344,
    346,
    349,
    380,
    384,
    393,
    394,
    397,
    398,
    406,
    407,
    408,
    409
  ],
  "406": [
    1,
    8,
    9,
    16,
    30,
    33,
    306,
    307,
    308,
    309,
    316,
    318,
    321,
    330,
    334,
    349,
    380,
    384,
    393,
    394,
    397,
    398,
    407,
    408,
    409
  ],
  "407": [
    8,
    9,
    16,
    30,
    33,
    75,
    78,
    80,
    100,
    255,
    300,
    302,
    304,
    318,
    321,
    330,
    334,
    336,
    342,
    344,
    346,
    349,
    373,
    374,
    380,
    381,
    382,
    383,
    393,
    394,
    397,
    405,
    406,
    408,
    409
  ],
  "408": [
    1,
    9,
    16,
    30,
    316,
    318,
    321,
    330,
    334,
    336,
    394,
    405,
    406,
    407
  ],
  "409": [
    16,
    18,
    30,
    33,
    255,
    318,
    342,
    344,
    345,
    346,
    380,
    405,
    406,
    407
  ],
  "410": [
    1,
    7,
    8,
    9,
    12,
    13,
    14,
    15,
    33,
    108,
    162,
    163,
    164,
    178,
    196,
    235,
    256,
    257,
    259,
    276,
    297,
    411
  ],
  "411": [
    1,
    3,
    7,
    11,
    13,
    140,
    162,
    163,
    164,
    196,
    202,
    256,
    410
  ],
  "412": [
    146,
    148,
    156,
    166,
    168,
    170,
    183,
    188,
    194,
    195,
    200,
    240,
    278,
    279,
    283,
    284,
    285,
    287,
    288
  ],
  "413": [
    145,
    163,
    271
  ],
  "414": [
    1,
    196,
    271,
    272,
    274,
    275,
    277,
    278,
    279,
    305,
    321
  ],
  "415": [
    182,
    188,
    194,
    198,
    278,
    279,
    282,
    284
  ],
  "416": [
    12,
    109,
    133,
    156,
    158,
    163,
    242,
    271,
    410
  ],
  "417": [
    178,
    179,
    182,
    183,
    187,
    188,
    190
  ],
  "418": [
    1,
    2,
    3,
    30,
    190,
    269,
    280,
    290,
    291,
    293
  ],
  "419": [
    1,
    9,
    20,
    30,
    55,
    298,
    308,
    309,
    310,
    311,
    319,
    342,
    348,
    349,
    350,
    351,
    352,
    369,
    370,
    372,
    373,
    403
  ],
  "420": [
    9,
    255,
    257,
    259,
    265,
    377,
    410
  ],
  "421": [
    1,
    5,
    120,
    233,
    234
  ],
  "422": [],
  "423": [
    5,
    7,
    11,
    162,
    163,
    164,
    411
  ]
}